Metadata-Version: 2.1
Name: flake8-newspaper-style
Version: 0.4.2
Summary: Check code for newspaper style
Home-page: https://github.com/mobility-university/flake8-newspaper-style
Author: think
Author-email: who@knows.me
License: MIT
Platform: UNKNOWN
Classifier: Programming Language :: Python :: 3.7
Classifier: Programming Language :: Python :: 3.8
Classifier: Programming Language :: Python :: 3.9
Classifier: Programming Language :: Python :: 3.10
Classifier: Framework :: Flake8
License-File: LICENSE
